{
	"w01y.kancolle-server.com": {
		"name": "横須賀鎮守府"
	},
	"w02k.kancolle-server.com": {
		"name": "呉鎮守府"
	},
	"w03s.kancolle-server.com": {
		"name": "佐世保鎮守府"
	},
	"w04m.kancolle-server.com": {
		"name": "舞鶴鎮守府"
	},
	"w05o.kancolle-server.com": {
		"name": "大湊警備府"
	},
	"w06t.kancolle-server.com": {
		"name": "トラック泊地"
	},
	"w07l.kancolle-server.com": {
		"name": "リンガ泊地"
	},
	"w08r.kancolle-server.com": {
		"name": "ラバウル基地"
	},
	"w09s.kancolle-server.com": {
		"name": "ショートランド泊地"
	},
	"w10b.kancolle-server.com": {
		"name": "ブイン基地"
	},
	"w11t.kancolle-server.com": {
		"name": "タウイタウイ泊地"
	},
	"w12p.kancolle-server.com": {
		"name": "パラオ泊地"
	},
	"w13b.kancolle-server.com": {
		"name": "ブルネイ泊地"
	},
	"w14h.kancolle-server.com": {
		"name": "単冠湾泊地"
	},
	"w15p.kancolle-server.com": {
		"name": "幌筵泊地"
	},
	"w16s.kancolle-server.com": {
		"name": "宿毛湾泊地"
	},
	"w17k.kancolle-server.com": {
		"name": "鹿屋基地"
	},
	"w18i.kancolle-server.com": {
		"name": "岩川基地"
	},
	"w19s.kancolle-server.com": {
		"name": "佐伯湾泊地"
	},
	"w20h.kancolle-server.com": {
		"name": "柱島泊地"
	}
}
